{
  "alphabet": [
    "a",
    "b"
  ],
  "states": [
    "3",
    "6",
    "0",
    "2",
    "11",
    "4",
    "5",
    "7",
    "9",
    "1"
  ],
  "initial_state": "0",
  "accepting_states": [
    "11"
  ],
  "transitions": [
    [
      "0",
      "a",
      "1"
    ],
    [
      "4",
      "b",
      "5"
    ],
    [
      "2",
      "a",
      "3"
    ],
    [
      "6",
      "\u03b5",
      "4"
    ],
    [
      "6",
      "\u03b5",
      "2"
    ],
    [
      "5",
      "\u03b5",
      "7"
    ],
    [
      "3",
      "\u03b5",
      "7"
    ],
    [
      "7",
      "\u03b5",
      "6"
    ],
    [
      "1",
      "\u03b5",
      "6"
    ],
    [
      "7",
      "\u03b5",
      "9"
    ],
    [
      "1",
      "\u03b5",
      "9"
    ],
    [
      "9",
      "b",
      "11"
    ]
  ]
}